controller.v
module control (clock, hwy, cntry, X, clear);
   
    parameter RED=2'b00,YELLOW=2'b01,GREEN=2'b10;
    parameter TRUE=1'b1, FALSE=1'b0;

  // State Definition       HWY     CNTRY    
    parameter S0=3'd0; // GREEN     RED
    parameter S1=3'd1; // YELLOW    RED
    parameter S2=3'd2; //  RED      RED
    parameter S3=3'd3; //  RED      GREEN
    parameter S4=3'd4; //  RED      YELLOW

    output reg [1:0] hwy,cntry;
    input X;        //TRUE indicates that car is present on
                    //country road, else FALSE
    input clear,clock;

    //Internal State Variables
    reg [2:0] state;
    reg [2:0] next_state;

    //Control Starts in state S0
    initial
    begin
        state <= S0;
        next_state <= S0;
        hwy <= GREEN;
        cntry <= RED;    
    end

    //State Changes only on psoitive edge of clock
    always @(posedge clock)
    begin
      state <= next_state;  
    end

    always@(state)      // State Definition
    begin
        case (state)
           S0 : begin
                    hwy <= GREEN;
                    cntry <= RED;
                end
           S1 : begin
                    hwy <= YELLOW;
                    cntry <= RED;
                end        
           S2 : begin
                    hwy <= RED;
                    cntry <= RED;
                end 
           S3 : begin
                    hwy <= RED;
                    cntry <= GREEN;
                end
           S4 : begin
                    hwy <= RED;
                    cntry <= YELLOW;
                end       
            endcase
    end

    always@(state or clear or X)    //Logic (FSM)
    begin
        if(clear)
            next_state <= S0;
        else
            case(state)
            S0 : if(X)
                    next_state <= S1;
                 else
                    next_state <= S0;
            S1 : begin  //delay some positive edges of clock
                    repeat(3) @(posedge clock);
                    next_state <= S2;
                 end 
            S2 : begin  //delay some positive edges of clock
                    repeat(2) @(posedge clock);
                    next_state <= S3;
                 end               
            S3 : if(X)
                    next_state <= S3;
                 else
                    next_state <= S4;
            S4 : begin  //delay some positive edges of clock
                    repeat(3) @(posedge clock);
                    next_state <= S0;
                 end   
            default: next_state <= S0;
            endcase
    end                         
endmodule

test.v
module traffic_test;

reg clock,X,clear;
wire [1:0] hwy,cntry;
control test(clock,hwy,cntry,X,clear);

initial begin
    clock=0;
    repeat(50)
    begin
    #5 clock= 1;
    #5 clock =0;
    end
end

initial
    begin
        #3 clear=1'b1; X=1'b0;
        #5 clear=1 ;X=1;
        #5 clear=0 ;X=1;
        #25 clear=0;X=1;
        #5 clear=0 ;X=0;
    end
    initial
    begin
        $dumpfile ("cont.vcd");
        $dumpvars (0,traffic_test);
        #300 $finish;
    end

endmodule

cont.vcd
$date
	Tue Jul 09 02:58:45 2024
$end
$version
	Icarus Verilog
$end
$timescale
	1s
$end
$scope module traffic_test $end
$var wire 2 ! hwy [1:0] $end
$var wire 2 " cntry [1:0] $end
$var reg 1 # X $end
$var reg 1 $ clear $end
$var reg 1 % clock $end
$scope module test $end
$var wire 1 # X $end
$var wire 1 $ clear $end
$var wire 1 % clock $end
$var parameter 1 & FALSE $end
$var parameter 2 ' GREEN $end
$var parameter 2 ( RED $end
$var parameter 3 ) S0 $end
$var parameter 3 * S1 $end
$var parameter 3 + S2 $end
$var parameter 3 , S3 $end
$var parameter 3 - S4 $end
$var parameter 1 . TRUE $end
$var parameter 2 / YELLOW $end
$var reg 2 0 cntry [1:0] $end
$var reg 2 1 hwy [1:0] $end
$var reg 3 2 next_state [2:0] $end
$var reg 3 3 state [2:0] $end
$upscope $end
$upscope $end
$enddefinitions $end
$comment Show the parameter values. $end
$dumpall
b1 /
1.
b100 -
b11 ,
b10 +
b1 *
b0 )
b0 (
b10 '
0&
$end
#0
$dumpvars
b0 3
b0 2
b10 1
b0 0
0%
x$
x#
b0 "
b10 !
$end
#3
0#
1$
#5
1%
#8
1#
#10
0%
#13
b1 2
0$
#15
b1 !
b1 1
b1 3
1%
#20
0%
#25
1%
#30
0%
#35
1%
#40
0%
#43
0#
#45
b10 2
1%
#50
0%
#55
b0 !
b0 1
b10 3
1%
#60
0%
#65
1%
#70
0%
#75
b11 2
1%
#80
0%
#85
b100 2
b10 "
b10 0
b11 3
1%
#90
0%
#95
b1 "
b1 0
b100 3
1%
#100
0%
#105
1%
#110
0%
#115
1%
#120
0%
#125
b0 2
1%
#130
0%
#135
b0 "
b0 0
b10 !
b10 1
b0 3
1%
